classopt/__init__.py
classopt/config.py
classopt/decorator.py
classopt/inheritance.py
classopt/utils.py
classopt-0.2.1.dist-info/LICENSE
classopt-0.2.1.dist-info/WHEEL
classopt-0.2.1.dist-info/METADATA
classopt-0.2.1.dist-info/RECORD
