Metadata-Version: 2.1
Name: classopt
Version: 0.2.1
Summary: Arguments parser with class for Python, inspired by StructOpt
Home-page: https://github.com/moisutsu/classopt
Author: moisutsu
Author-email: moisutsu@gmail.com
Requires-Python: >=3.7,<4.0
Classifier: Programming Language :: Python :: 3
Classifier: Programming Language :: Python :: 3.10
Classifier: Programming Language :: Python :: 3.7
Classifier: Programming Language :: Python :: 3.8
Classifier: Programming Language :: Python :: 3.9
Project-URL: Repository, https://github.com/moisutsu/classopt
